tohe/__init__.py
tohe/cli.py
tohe/db/__init__.py
tohe/db/db.py
tohe/log/__init__.py
tohe/util/__init__.py
tohe/util/editor.py
tohe/util/status.py
tohe-0.2.1.dist-info/entry_points.txt
tohe-0.2.1.dist-info/LICENSE
tohe-0.2.1.dist-info/WHEEL
tohe-0.2.1.dist-info/METADATA
tohe-0.2.1.dist-info/RECORD
