Metadata-Version: 2.1
Name: tohe
Version: 0.2.1
Summary: tohe - The friendly TODO list helper
License: MIT
Author: Lukas Deutz
Author-email: lukas.deutz@mailfence.com
Requires-Python: >=3.5,<4.0
Classifier: Development Status :: 3 - Alpha
Classifier: License :: OSI Approved :: MIT License
Classifier: Programming Language :: Python :: 3
Classifier: Programming Language :: Python :: 3.5
Classifier: Programming Language :: Python :: 3.6
Classifier: Programming Language :: Python :: 3.7
Classifier: Programming Language :: Python :: 3.8
Classifier: Topic :: Utilities
Requires-Dist: colorama (>=0.4.3,<0.5.0)
